chatan/__init__.py
chatan/dataset.py
chatan/evaluate.py
chatan/generator.py
chatan/sampler.py
chatan/viewer.py
chatan-0.3.0.dist-info/METADATA
chatan-0.3.0.dist-info/WHEEL
chatan-0.3.0.dist-info/licenses/LICENSE
chatan-0.3.0.dist-info/RECORD
