Metadata-Version: 2.4
Name: chatan
Version: 0.3.0
Summary: Create synthetic datasets with LLM generators and samplers
Project-URL: Documentation, https://github.com/cdreetz/chatan#readme
Project-URL: Issues, https://github.com/cdreetz/chatan/issues
Project-URL: Source, https://github.com/cdreetz/chatan
Author-email: Christian Reetz <cdreetz@gmail.com>
License-Expression: MIT
License-File: LICENSE
Keywords: dataset generation,llm,machine learning,synthetic data
Classifier: Development Status :: 4 - Beta
Classifier: Intended Audience :: Developers
Classifier: License :: OSI Approved :: MIT License
Classifier: Operating System :: OS Independent
Classifier: Programming Language :: Python :: 3
Classifier: Programming Language :: Python :: 3.8
Classifier: Programming Language :: Python :: 3.9
Classifier: Programming Language :: Python :: 3.10
Classifier: Programming Language :: Python :: 3.11
Classifier: Programming Language :: Python :: 3.12
Classifier: Topic :: Scientific/Engineering :: Artificial Intelligence
Classifier: Topic :: Software Development :: Libraries :: Python Modules
Requires-Python: >=3.8
Requires-Dist: anthropic>=0.7.0
Requires-Dist: datasets>=2.0.0
Requires-Dist: numpy>=1.20.0
Requires-Dist: openai>=1.0.0
Requires-Dist: pandas>=1.3.0
Requires-Dist: pydantic>=2.0.0
Requires-Dist: pytest-asyncio>=0.24.0
Requires-Dist: ruff>=0.14.0
Requires-Dist: tqdm>=4.0.0
Provides-Extra: all
Requires-Dist: nltk>=3.9.1; extra == 'all'
Requires-Dist: scikit-learn>=1.3.2; extra == 'all'
Requires-Dist: sentence-transformers>=3.2.1; extra == 'all'
Requires-Dist: torch>=2.5.1; extra == 'all'
Requires-Dist: transformers>=4.0.0; extra == 'all'
Provides-Extra: eval
Requires-Dist: nltk>=3.9.1; extra == 'eval'
Requires-Dist: scikit-learn>=1.3.2; extra == 'eval'
Requires-Dist: sentence-transformers>=3.2.1; extra == 'eval'
Provides-Extra: local
Requires-Dist: torch>=2.5.1; extra == 'local'
Requires-Dist: transformers>=4.0.0; extra == 'local'
